image_center/__init__.py
image_center/__version__.py
image_center/conf.py
image_center/server.py
image_center-2024.6.5.dist-info/METADATA
image_center-2024.6.5.dist-info/WHEEL
image_center-2024.6.5.dist-info/licenses/LICENSE
image_center-2024.6.5.dist-info/RECORD
