Metadata-Version: 2.1
Name: image-center
Version: 2024.6.5
Summary: image-center
Project-URL: Source, https://github.com/linuxdeepin/image-center
Project-URL: Documentation, https://linuxdeepin.github.io/image-center
Author-email: mikigo <1964191531@qq.com>
License-File: LICENSE
Classifier: License :: OSI Approved :: Apache Software License
Classifier: Operating System :: OS Independent
Classifier: Programming Language :: Python :: 3
Requires-Python: >=3.6
Requires-Dist: pillow
Requires-Dist: pyscreenshot
Provides-Extra: doc
Requires-Dist: mkdocs-material; extra == 'doc'
Provides-Extra: test
Requires-Dist: pytest; extra == 'test'
